README.md
setup.cfg
setup.py
bonapity/__init__.py
bonapity/code_generation.py
bonapity/decoration_classes.py
bonapity/decorators.py
bonapity/html_generation.py
bonapity/json_encode.py
bonapity/mime.py
bonapity/server.py
bonapity/session.py
bonapity.egg-info/PKG-INFO
bonapity.egg-info/SOURCES.txt
bonapity.egg-info/dependency_links.txt
bonapity.egg-info/not-zip-safe
bonapity.egg-info/top_level.txt