Metadata-Version: 2.1
Name: bonapity
Version: 0.1.20
Summary: Get a simple HTTP (REST) API with only this simple decorator : @bonapity !
Home-page: https://vievie31.github.io/bonapity/
Author: Olivier RISSER-MAROIX
Author-email: orissermaroix@gmail.com
License: CC-BY
Platform: UNKNOWN
